addressbook/__init__.py
addressbook/command_matcher.py
addressbook/error_handler.py
addressbook/main.py
addressbook/utils.py
addressbook/address_book/__init__.py
addressbook/address_book/address_book.py
addressbook/address_book/handlers.py
addressbook/note_book/__init__.py
addressbook/note_book/handlers.py
addressbook/note_book/note_book.py
goit_dev_nest_addressbook_cli-0.3.0.dist-info/METADATA
goit_dev_nest_addressbook_cli-0.3.0.dist-info/WHEEL
goit_dev_nest_addressbook_cli-0.3.0.dist-info/entry_points.txt
goit_dev_nest_addressbook_cli-0.3.0.dist-info/top_level.txt
goit_dev_nest_addressbook_cli-0.3.0.dist-info/RECORD
